Metadata-Version: 1.1
Name: irobot
Version: 1.0.4
Summary: The irobot project
Home-page: https://pypi.python.org/pypi/irobot
Author: nobody
Author-email: 2273337844@qq.com
License: Apache
Keywords: irobot robot
Platform: Linux
Platform: Unix
Classifier: Programming Language :: Python :: 3
Classifier: Programming Language :: Python :: 3.5
